reggol/__init__.py
reggol/colored_formatter.py
reggol/logger.py
reggol-0.2.0.dist-info/LICENSE
reggol-0.2.0.dist-info/METADATA
reggol-0.2.0.dist-info/WHEEL
reggol-0.2.0.dist-info/top_level.txt
reggol-0.2.0.dist-info/RECORD
