Metadata-Version: 2.1
Name: reggol
Version: 0.2.0
Summary: Reggol is a convenience layer over python's logging module.
Home-page: https://github.com/roboy/ravestate
Author: Roboy
Author-email: info@roboy.org
License: UNKNOWN
Platform: UNKNOWN
Classifier: Programming Language :: Python :: 3
Classifier: Operating System :: OS Independent
Requires-Python: >=3.6
